Metadata-Version: 2.1
Name: odoo13-addon-delivery-state
Version: 13.0.2.0.3
Summary: Provides fields to be able to contemplate the tracking statesand also adds a global fields
Home-page: https://github.com/OCA/delivery-carrier
Author: Trey (www.trey.es), FactorLibre, Tecnativa, Odoo Community Association (OCA)
Author-email: support@odoo-community.org
License: AGPL-3
Platform: UNKNOWN
Classifier: Programming Language :: Python
Classifier: Framework :: Odoo
Classifier: Framework :: Odoo :: 13.0
Classifier: License :: OSI Approved :: GNU Affero General Public License v3
Classifier: Development Status :: 5 - Production/Stable
Requires-Python: >=3.5
Requires-Dist: odoo (<13.1dev,>=13.0a)
